kDic/__init__.py
kdic-1.0.10.dist-info/LICENSE
kdic-1.0.10.dist-info/METADATA
kdic-1.0.10.dist-info/WHEEL
kdic-1.0.10.dist-info/top_level.txt
kdic-1.0.10.dist-info/RECORD
