Metadata-Version: 2.1
Name: kdic
Version: 1.0.10
Summary: Extended Dictionary
Home-page: https://github.com/kagepark/kDict
Author: Kage Park
License: MIT
Platform: UNKNOWN
Classifier: Programming Language :: Python :: 2
Classifier: Programming Language :: Python :: 3
Classifier: License :: OSI Approved :: MIT License
Classifier: Operating System :: OS Independent
License-File: LICENSE
